companionsKQML/__init__.py
companionsKQML/companionsKQMLDispatcher.py
companionsKQML/companionsKQMLModule.py
companionsKQML/pythonian.py
companionsKQML-1.1.4.dist-info/LICENSE
companionsKQML-1.1.4.dist-info/METADATA
companionsKQML-1.1.4.dist-info/WHEEL
companionsKQML-1.1.4.dist-info/top_level.txt
companionsKQML-1.1.4.dist-info/RECORD
