Metadata-Version: 2.1
Name: companionsKQML
Version: 1.1.4
Summary: Companions agents in Python.
Home-page: http://github.com/SamuelHill/companionsKQML
Author: Samuel J. Hill
Author-email: samuelhill2022@northwestern.edu
License: UNKNOWN
Project-URL: Qualitative Reasoning Group, http://www.qrg.northwestern.edu/
Platform: UNKNOWN
Classifier: Development Status :: 4 - Beta
Classifier: Environment :: Console
Classifier: Intended Audience :: Science/Research
Classifier: License :: OSI Approved :: BSD License
Classifier: Operating System :: OS Independent
Classifier: Programming Language :: Python :: 3
Requires-Python: >=3.0
Requires-Dist: pykqml (>=1.3)
Requires-Dist: psutil (>=5.6.5)
Requires-Dist: python-dateutil (>=2.8.1)
